py_ankiconnect/__init__.py
py_ankiconnect/__main__.py
py_ankiconnect/help.py
py_ankiconnect/py_ankiconnect.py
py_ankiconnect-1.1.4.dist-info/licenses/LICENSE
py_ankiconnect-1.1.4.dist-info/METADATA
py_ankiconnect-1.1.4.dist-info/WHEEL
py_ankiconnect-1.1.4.dist-info/entry_points.txt
py_ankiconnect-1.1.4.dist-info/top_level.txt
py_ankiconnect-1.1.4.dist-info/RECORD
