Metadata-Version: 2.4
Name: py-ankiconnect
Version: 1.1.4
Summary: Minimal wrapper to simplify the usage of the awesome ankiconnect anki addon.
Home-page: https://github.com/thiswillbeyourgithub/py_ankiconnect
Keywords: anki,flashcards,ankiconnect,learning,cli,tool,spaced,repetition,ebbinghaus,addon
Classifier: Programming Language :: Python :: 3
Classifier: Operating System :: OS Independent
Requires-Python: >=3.9
License-File: LICENSE
Requires-Dist: fire>=0.6.0
Requires-Dist: aiohttp
Provides-Extra: rich
Requires-Dist: rich; extra == "rich"
Dynamic: classifier
Dynamic: description
Dynamic: description-content-type
Dynamic: home-page
Dynamic: keywords
Dynamic: license-file
Dynamic: provides-extra
Dynamic: requires-dist
Dynamic: requires-python
Dynamic: summary
